main/MorseDecode.py
main/__init__.py
Morse_Translator-0.1.dist-info/METADATA
Morse_Translator-0.1.dist-info/WHEEL
Morse_Translator-0.1.dist-info/entry_points.txt
Morse_Translator-0.1.dist-info/top_level.txt
Morse_Translator-0.1.dist-info/RECORD
