Metadata-Version: 2.1
Name: Morse Translator
Version: 0.1
Summary: Trivial Package Testing
Home-page: https://github.com/Tylerastro/MorseCode
Author: Tylerastro
License: MIT
Platform: UNKNOWN
Classifier: Development Status :: 2 - Pre-Alpha
Requires-Python: >=3
